{
  "question_id": null,
  "course": "DSA1101",
  "semester": "AY 2024/25 Sem 2",
  "assessment_type": "Quiz",
  "question_no": 3,
  "is_multi": false,
  "question_stem": "Question 3\nWhich variable is the most insignificant in this model?\nA\nAge\nB\nMarried\nC\nCust_years\nD\nChurned_contacts",
  "question_stem_html": "<pre>Question 3\nWhich variable is the most insignificant in this model?\nA\nAge\nB\nMarried\nC\nCust_years\nD\nChurned_contacts</pre>",
  "version": 1,
  "update_timestamp": "2025-10-05T22:35:13+08:00",
  "question_media": [],
  "items": [
    {
      "part_number": "a",
      "type": "mcq",
      "subtype": "single",
      "part_stem": "Answer the question.",
      "part_stem_html": "<p>Answer the question.</p>",
      "choices": [
        {
          "choice_id": null,
          "text": "B",
          "text_html": "<p>B</p>",
          "is_correct": null,
          "explanation": null
        },
        {
          "choice_id": null,
          "text": "arried",
          "text_html": "<p>arried</p>",
          "is_correct": null,
          "explanation": null
        },
        {
          "choice_id": null,
          "text": "C",
          "text_html": "<p>C</p>",
          "is_correct": null,
          "explanation": null
        },
        {
          "choice_id": null,
          "text": "ust_years",
          "text_html": "<p>ust_years</p>",
          "is_correct": null,
          "explanation": null
        },
        {
          "choice_id": null,
          "text": "D",
          "text_html": "<p>D</p>",
          "is_correct": null,
          "explanation": null
        },
        {
          "choice_id": null,
          "text": "hurned_contacts",
          "text_html": "<p>hurned_contacts</p>",
          "is_correct": null,
          "explanation": null
        }
      ],
      "items_media": [],
      "scoring": {
        "points": null
      },
      "feedback": {},
      "shuffle_choices": false,
      "solution": null,
      "solution_html": null,
      "difficulty_level": null,
      "concept_tags": []
    }
  ]
}